<?xml version="1.0" encoding="UTF-8"?>
<java version="21.0.4" class="java.beans.XMLDecoder">
 <object class="java.util.ArrayList">
  <void method="add">
   <object class="programacion3.laboratorio1.Clases.Club.Profesor">
    <void property="nombre">
     <string>Juan</string>
    </void>
   </object>
  </void>
  <void method="add">
   <object class="programacion3.laboratorio1.Clases.Club.Profesor">
    <void property="nombre">
     <string>Maria</string>
    </void>
   </object>
  </void>
  <void method="add">
   <object class="programacion3.laboratorio1.Clases.Club.Profesor">
    <void property="nombre">
     <string>Pedro</string>
    </void>
   </object>
  </void>
 </object>
</java>
